[
  {
    "primary": {
      "rgb": [
        "6",
        "0",
        "71"
      ],
      "hex": "060047"
    },
    "secondary": {
      "rgb": [
        "179",
        "0",
        "94"
      ],
      "hex": "B3005E"
    },
    "third": {
      "rgb": [
        "233",
        "0",
        "100"
      ],
      "hex": "E90064"
    },
    "forth": {
      "rgb": [
        "255",
        "95",
        "158"
      ],
      "hex": "FF5F9E"
    }
  },
  {
    "primary": {
      "rgb": [
        "77",
        "69",
        "93"
      ],
      "hex": "4D455D"
    },
    "secondary": {
      "rgb": [
        "233",
        "100",
        "121"
      ],
      "hex": "E96479"
    },
    "third": {
      "rgb": [
        "245",
        "233",
        "207"
      ],
      "hex": "F5E9CF"
    },
    "forth": {
      "rgb": [
        "125",
        "185",
        "182"
      ],
      "hex": "7DB9B6"
    }
  },
  {
    "primary": {
      "rgb": [
        "43",
        "52",
        "103"
      ],
      "hex": "2B3467"
    },
    "secondary": {
      "rgb": [
        "186",
        "215",
        "233"
      ],
      "hex": "BAD7E9"
    },
    "third": {
      "rgb": [
        "252",
        "255",
        "231"
      ],
      "hex": "FCFFE7"
    },
    "forth": {
      "rgb": [
        "235",
        "69",
        "95"
      ],
      "hex": "EB455F"
    }
  },
  {
    "primary": {
      "rgb": [
        "83",
        "145",
        "101"
      ],
      "hex": "539165"
    },
    "secondary": {
      "rgb": [
        "63",
        "73",
        "127"
      ],
      "hex": "3F497F"
    },
    "third": {
      "rgb": [
        "247",
        "192",
        "74"
      ],
      "hex": "F7C04A"
    },
    "forth": {
      "rgb": [
        "248",
        "245",
        "228"
      ],
      "hex": "F8F5E4"
    }
  },
  {
    "primary": {
      "rgb": [
        "78",
        "110",
        "129"
      ],
      "hex": "4E6E81"
    },
    "secondary": {
      "rgb": [
        "249",
        "219",
        "187"
      ],
      "hex": "F9DBBB"
    },
    "third": {
      "rgb": [
        "255",
        "3",
        "3"
      ],
      "hex": "FF0303"
    },
    "forth": {
      "rgb": [
        "46",
        "56",
        "64"
      ],
      "hex": "2E3840"
    }
  }
]
